effortlessHTML/__init__.py
effortlessHTML/attributes/__init__.py
effortlessHTML/attributes/base.py
effortlessHTML/elements/__init__.py
effortlessHTML/elements/base.py
effortlesshtml-0.1.1.dist-info/LICENSE
effortlesshtml-0.1.1.dist-info/METADATA
effortlesshtml-0.1.1.dist-info/WHEEL
effortlesshtml-0.1.1.dist-info/RECORD
