Metadata-Version: 2.1
Name: effortlesshtml
Version: 0.1.1
Summary: Simple python templating engine for html
Author: Togo
Author-email: TogoTheBlackDog@panther.com
Requires-Python: >=3.11,<4.0
Classifier: Programming Language :: Python :: 3
Classifier: Programming Language :: Python :: 3.11
